arpq/__init__.py
arpq/abc.py
arpq/encoders.py
arpq/message.py
arpq/queue.py
arpq/types.py
arpq-0.1.1.dist-info/LICENSE
arpq-0.1.1.dist-info/METADATA
arpq-0.1.1.dist-info/WHEEL
arpq-0.1.1.dist-info/top_level.txt
arpq-0.1.1.dist-info/RECORD
