Metadata-Version: 2.1
Name: arpq
Version: 0.1.1
Summary: Asynchronous python library impementing priority queue based on Redis sorted sets
Home-page: https://github.com/ModBayNet/arpq
Author: Eugene Ershov
Author-email: oss@modbay.net
License: MIT
Platform: UNKNOWN
Classifier: Development Status :: 3 - Alpha
Classifier: Intended Audience :: Developers
Classifier: Programming Language :: Python
Classifier: Programming Language :: Python :: 3
Classifier: Programming Language :: Python :: 3.7
Classifier: Programming Language :: Python :: 3.8
Classifier: Programming Language :: Python :: Implementation :: CPython
Classifier: Programming Language :: Python :: Implementation :: PyPy
Classifier: Operating System :: OS Independent
Classifier: License :: OSI Approved :: MIT License
Classifier: Natural Language :: English
Classifier: Topic :: Software Development :: Object Brokering
Classifier: Typing :: Typed
Requires-Python: >=3.7
Requires-Dist: aioredis
